scpi_pkg/__init__.py
scpi_pkg/funs.py
scpi_pkg/scdata.py
scpi_pkg/scdataMulti.py
scpi_pkg/scest.py
scpi_pkg/scpi.py
scpi_pkg/scplot.py
scpi_pkg/scplotMulti.py
scpi_pkg/version.py
scpi_pkg-2.2.7.dist-info/LICENSE
scpi_pkg-2.2.7.dist-info/METADATA
scpi_pkg-2.2.7.dist-info/WHEEL
scpi_pkg-2.2.7.dist-info/top_level.txt
scpi_pkg-2.2.7.dist-info/RECORD
