Metadata-Version: 2.1
Name: scpi-pkg
Version: 2.2.7
Summary: The package computes point estimates and prediction intervals for Synthetic Control methods as proposed in Cattaneo, Feng, and Titiunik (2021).
Home-page: https://nppackages.github.io/scpi/
Author: Filippo Palomba
Author-email: fpalomba@princeton.edu
Project-URL: Bug Tracker, https://nppackages.github.io/scpi/
Classifier: Programming Language :: Python :: 3
Classifier: License :: OSI Approved :: MIT License
Classifier: Operating System :: OS Independent
Requires-Python: >=3.7
License-File: LICENSE
Requires-Dist: cvxpy >=1.1.18
Requires-Dist: dask >=2021.04.0
Requires-Dist: ecos >=2.0.7
Requires-Dist: luddite >=1.0.2
Requires-Dist: numpy >=1.20.1
Requires-Dist: pandas >=1.5.0
Requires-Dist: plotnine >=0.8.0
Requires-Dist: scikit-learn >=0.24.1
Requires-Dist: scipy >=1.7.1
Requires-Dist: statsmodels >=0.12.2
